aplicacion_ventas/__init__.py
aplicacion_ventas/descuentos.py
aplicacion_ventas/exceptions.py
aplicacion_ventas/gestos_ventas.py
aplicacion_ventas/impuestos.py
aplicacion_ventas/precios.py
aplicacion_ventas_rlivia-0.1.0.dist-info/licenses/LICENCE
tests/__init__.py
tests/test_aplicacion_venta.py
aplicacion_ventas_rlivia-0.1.0.dist-info/METADATA
aplicacion_ventas_rlivia-0.1.0.dist-info/WHEEL
aplicacion_ventas_rlivia-0.1.0.dist-info/top_level.txt
aplicacion_ventas_rlivia-0.1.0.dist-info/RECORD
