Metadata-Version: 2.4
Name: aplicacion_ventas_rlivia
Version: 0.1.0
Summary: Paquete para gestionar ventas, impuestos y descuentos
Home-page: https://github.com/curso_python/aplicativoventas
Author: Ray Livia
Author-email: rayoliviap@gmail.com
Classifier: Programming Language :: Python :: 3
Classifier: Programming Language :: Python :: 3.13
Classifier: License :: OSI Approved :: MIT License
Classifier: Operating System :: OS Independent
Requires-Python: >=3.7
License-File: LICENCE
Dynamic: author
Dynamic: author-email
Dynamic: classifier
Dynamic: description
Dynamic: description-content-type
Dynamic: home-page
Dynamic: license-file
Dynamic: requires-python
Dynamic: summary
